{
    "data" :  {
    "ref": "QH3-P0015",
    "price": "135000",
    "ptype" : "Quadhouse",
    "plot" : "100",
    "living" : "72",
    "location" : "Playa Flamenca",
    "town": "Orihuela Costa",
    "province": "Alicante",
    "costa": "Costa Blanca Süd",
    "community": "Valencia",
    "beds": "3",
    "baths": "2",
    "pool": "Gemeinschafts",
    "url": "6231550869897216-Quadhouse-zu-verkaufen-Playa-Flamenca/",
    "desc":"We are pleased to present you this east-south facing quad in a gated residence in Playa  Flamenca, close to all amenities, like the sports centre, the famous Zenia Boulevard, the  sea and beaches, restaurants, bars, supermarkets, schools, t",
    "thumb":"https://lh3.googleusercontent.com/seBbJPBDMIUjZqjoL5JvthQUr9YCNqSYORz6bqEbFMjCA0ZBEeQ9P8-3dmROwTnKiDVuO_QIGKVcOQ6Fhnc=w400-h240-n-rj-e30-l100"
}
 
}
